{
  "Late Triassic": {
    "USA": [38, -117],
    "Canada": [56, -126],
    "England": [52, -21],
    "France": [44, -16],
    "Germany": [49, -8],
    "China": [35, 84],
    "Mongolia": [46, 85],
    "Argentina": [-34, -84],
    "Brazil": [-14, -71],
    "Morocco": [31, -27],
    "South Africa": [-30, 5],
    "Australia": [-25, 113],
    "India": [20, 58],
    "Russia": [60, 80],
    "Portugal": [39, -28],
    "Spain": [40, -23],
    "Mexico": [23, -122],
    "Egypt": [26, 10],
    "Niger": [17, -11],
    "Romania": [46, 5],
    "Austria": [47, -7],
    "Belgium": [50, -16],
    "Switzerland": [47, -10],
    "Tanzania": [-6, 15],
    "Madagascar": [-18, 26],
    "Kazakhstan": [48, 47],
    "Uzbekistan": [41, 44],
    "Uruguay": [-33, -76],
    "Japan": [36, 118],
    "Wales": [52, -23],
    "Greenland": [72, -60],
    "Lesotho": [-29, 8],
    "Antarctica": [-82, 115],
    "Malawi": [-13, 14],
    "Zimbabwe": [-19, 9],
    "Algeria": [28, -17]
  },
  "Early Jurassic": {
    "USA": [20, -41],
    "Canada": [18, -52],
    "England": [39, 1],
    "France": [34, 7],
    "Germany": [41, 10],
    "China": [26, 118],
    "Mongolia": [30, 112],
    "Argentina": [-42, -65],
    "Brazil": [-30, -58],
    "Australia": [-42, 130],
    "Portugal": [14, -3],
    "Spain": [16, 0],
    "Mexico": [10, -78],
    "Egypt": [18, 7],
    "Niger": [12, 2],
    "Tanzania": [-8, 34],
    "Greenland": [53, -53],
    "Algeria": [16, 8],
    "South Africa": [-32, 26]
  },
  "Mid Jurassic": {
    "USA": [30, -41],
    "Canada": [16, -50],
    "England": [41, 9],
    "France": [36, 13],
    "Germany": [41, 18],
    "China": [28, 115],
    "Mongolia": [34, 110],
    "Argentina": [-40, -60],
    "Brazil": [-28, -55],
    "Australia": [-40, 132],
    "Portugal": [16, -1],
    "Spain": [18, 2],
    "Mexico": [12, -76],
    "Egypt": [20, 9],
    "Niger": [14, 4],
    "Tanzania": [-6, 36],
    "Greenland": [54, -50],
    "Algeria": [18, 10],
    "South Africa": [-30, 28]
  },
  "Late Jurassic": {
    "USA": [35, -48],
    "Canada": [14, -48],
    "England": [44, 8],
    "France": [37, 11],
    "Germany": [43, 17],
    "China": [30, 112],
    "Mongolia": [36, 108],
    "Argentina": [-38, -58],
    "Brazil": [-26, -52],
    "Australia": [-38, 134],
    "Portugal": [18, 1],
    "Spain": [20, 4],
    "Mexico": [14, -74],
    "Egypt": [22, 11],
    "Niger": [16, 6],
    "Tanzania": [-4, 38],
    "Greenland": [56, -48],
    "Algeria": [20, 12],
    "South Africa": [-28, 30]
  },
  "Early Cretaceous": {
    "USA": [38, -58],
    "Canada": [12, -46],
    "England": [41, 4],
    "France": [35, 7],
    "Germany": [41, 13],
    "China": [32, 110],
    "Mongolia": [38, 105],
    "Argentina": [-36, -55],
    "Brazil": [-24, -50],
    "Australia": [-36, 136],
    "Portugal": [20, 3],
    "Spain": [22, 6],
    "Mexico": [16, -72],
    "Egypt": [24, 13],
    "Niger": [18, 8],
    "Tanzania": [-2, 40],
    "Greenland": [57, -46],
    "Algeria": [22, 14],
    "South Africa": [-26, 32]
  },
  "Late Cretaceous": {
    "USA": [41, -65],
    "Canada": [10, -45],
    "England": [42, 1],
    "France": [36, 4],
    "Germany": [41, 10],
    "China": [34, 108],
    "Mongolia": [40, 102],
    "Argentina": [-34, -52],
    "Brazil": [-22, -48],
    "Australia": [-34, 138],
    "Portugal": [22, 5],
    "Spain": [24, 8],
    "Mexico": [18, -70],
    "Egypt": [26, 15],
    "Niger": [20, 10],
    "Tanzania": [0, 42],
    "Greenland": [58, -44],
    "Algeria": [24, 16],
    "South Africa": [-24, 34]
  }
}
